{
  "tabData": [
      { "title": "CNN", 
        "url": "http://www.cnn.com", 
        "favIconUrl": "http://www.cnn.com/favicon.ie9.ico" 
      },
      { "title": "wikipedia", 
        "url": "http://www.wikipedia.org/",
        "favIconUrl": "http://bits.wikimedia.org/favicon/wikipedia.ico" 
      },
      { "title": "Yahoo", 
        "url": "https://www.yahoo.com/",
        "favIconUrl": "https://s.yimg.com/rz/l/favicon.ico" },
      { "title": "wework", 
        "url": "https://www.wework.com/",
        "favIconUrl": "https://www.wework.com/favicon.ico" 
      },
      {
        "title": "Bootstrap · The world's most popular mobile-first and responsive front-end framework.",
        "url": "http://getbootstrap.com/",
        "favIconUrl": "http://getbootstrap.com/favicon.ico"
      },
      {
        "title": "CSS · Bootstrap",
        "url": "http://getbootstrap.com/css/",
        "favIconUrl": "http://getbootstrap.com/favicon.ico"
      },
      {
        "title": "Components · Bootstrap",
        "url": "http://getbootstrap.com/components/",
        "favIconUrl": "http://getbootstrap.com/favicon.ico"
      },
      {
        "title": "Please stop embedding Bootstrap classes in your HTML!",
        "url": "http://ruby.bvision.com/blog/please-stop-embedding-bootstrap-classes-in-your-html",
        "favIconUrl": "http://bvruby2.s3-us-west-1.amazonaws.com/assets/favicon-e07d08ebd70aa6e760e7904169b223a3.ico"
      },
      {
        "title": "X-Ray: A Scraper by the Author of Cheerio",
        "url": "http://dailyjs.com/2015/02/05/xray/",
        "favIconUrl": "http://dailyjs.com/favicon.ico"
      },
      {
        "title": "API Reference · mbostock/d3 Wiki",
        "url": "https://github.com/mbostock/d3/wiki/API-Reference",
        "favIconUrl": "https://assets-cdn.github.com/favicon.ico"
      },
      {
        "title": "Gallery · mbostock/d3 Wiki",
        "url": "https://github.com/mbostock/d3/wiki/Gallery",
        "favIconUrl": "https://assets-cdn.github.com/favicon.ico"
      },
      {
        "title": "Tutorials · mbostock/d3 Wiki",
        "url": "https://github.com/mbostock/d3/wiki/Tutorials",
        "favIconUrl": "https://assets-cdn.github.com/favicon.ico"
      },
      {
        "title": "Drag + Zoom",
        "url": "http://bl.ocks.org/mbostock/6123708",
        "favIconUrl": "http://bl.ocks.org/favicon.png"
      },
      {
        "title": "Focus+Context via Brushing",
        "url": "http://bl.ocks.org/mbostock/1667367",
        "favIconUrl": "http://bl.ocks.org/favicon.png"
      },
      {
        "title": "Extensions",
        "url": "chrome://extensions/",
        "favIconUrl": "chrome://theme/IDR_EXTENSIONS_FAVICON@2x"
      },
      {
        "title": "Welcome | Flask (A Python Microframework)",
        "url": "http://flask.pocoo.org/",
        "favIconUrl": "http://flask.pocoo.org/static/favicon.ico"
      },
      {
        "title": "GitHub",
        "url": "https://github.com/",
        "favIconUrl": "https://assets-cdn.github.com/favicon.ico"
      },
      {
        "title": "antonycourtney/tabman",
        "url": "https://github.com/antonycourtney/tabman",
        "favIconUrl": "https://assets-cdn.github.com/favicon.ico"
      },
      {
        "title": "antonycourtney (Antony Courtney)",
        "url": "https://github.com/antonycourtney",
        "favIconUrl": "https://assets-cdn.github.com/favicon.ico"
      },
      {
        "title": "Using Git subtrees for repository separation – Making Software",
        "url": "https://makingsoftware.wordpress.com/2013/02/16/using-git-subtrees-for-repository-separation/",
        "favIconUrl": "https://s2.wp.com/i/favicon.ico"
      },
      {
        "title": "https://www.haskell.org/onlinereport/haskell2010/",
        "url": "https://www.haskell.org/onlinereport/haskell2010/",
        "favIconUrl": "https://www.haskell.org/favicon.ico"
      },
      {
        "title": "Hoogle",
        "url": "https://www.haskell.org/hoogle/",
        "favIconUrl": "https://www.haskell.org/hoogle/res/favicon.png"
      },
      {
        "title": "The Haskell Platform: Contents",
        "url": "https://www.haskell.org/platform/contents.html#packages-and-documentation",
        "favIconUrl": "https://www.haskell.org/platform/images/Haskell-Logo-Boxed-32.png"
      },
      {
        "title": "Stackage Server",
        "url": "http://www.stackage.org/",
        "favIconUrl": "http://www.stackage.org/favicon.ico"
      },
      {
        "title": "jQuery UI API Documentation",
        "url": "http://api.jqueryui.com/",
        "favIconUrl": "http://api.jqueryui.com/jquery-wp-content/themes/api.jqueryui.com/i/favicon.ico"
      },
      {
        "title": "Node.js v0.12.2 Manual & Documentation",
        "url": "https://nodejs.org/api/",
        "favIconUrl": "https://nodejs.org/favicon.ico"
      },
      {
        "title": "File System Node.js v0.12.2 Manual & Documentation",
        "url": "https://nodejs.org/api/fs.html",
        "favIconUrl": "https://nodejs.org/favicon.ico"
      },
      {
        "title": "An Absolute Beginner's Guide to Node.js",
        "url": "http://blog.modulus.io/absolute-beginners-guide-to-nodejs",
        "favIconUrl": "http://blog.modulus.io/favicon-32x32.png"
      },
      {
        "title": "API · mapbox/node-sqlite3 Wiki",
        "url": "https://github.com/mapbox/node-sqlite3/wiki/API",
        "favIconUrl": "https://assets-cdn.github.com/favicon.ico"
      },
      {
        "title": "kriskowal/q",
        "url": "https://github.com/kriskowal/q",
        "favIconUrl": "https://assets-cdn.github.com/favicon.ico"
      },
      {
        "title": "API Reference · kriskowal/q Wiki",
        "url": "https://github.com/kriskowal/q/wiki/API-Reference",
        "favIconUrl": "https://assets-cdn.github.com/favicon.ico"
      },
      {
        "title": "josdejong/workerpool",
        "url": "https://github.com/josdejong/workerpool",
        "favIconUrl": "https://assets-cdn.github.com/favicon.ico"
      },
      {
        "title": "Underscore.js",
        "url": "http://underscorejs.org/",
        "favIconUrl": "http://underscorejs.org/favicon.ico"
      },
      {
        "title": "Overview — Python 2.7.10rc0 documentation",
        "url": "https://docs.python.org/2/",
        "favIconUrl": "https://docs.python.org/2/_static/py.png"
      },
      {
        "title": "The Python Tutorial — Python 2.7.10rc0 documentation",
        "url": "https://docs.python.org/2/tutorial/index.html",
        "favIconUrl": "https://docs.python.org/2/_static/py.png"
      },
      {
        "title": "The Python Standard Library — Python 2.7.10rc0 documentation",
        "url": "https://docs.python.org/2/library/index.html",
        "favIconUrl": "https://docs.python.org/2/_static/py.png"
      },
      {
        "title": "The Python Language Reference — Python 2.7.10rc0 documentation",
        "url": "https://docs.python.org/2/reference/index.html",
        "favIconUrl": "https://docs.python.org/2/_static/py.png"
      },
      {
        "title": "PEP 8 -- Style Guide for Python Code",
        "url": "http://legacy.python.org/dev/peps/pep-0008/",
        "favIconUrl": "http://legacy.python.org/favicon.ico"
      },
      {
        "title": "Reactive-Extensions/RxJS",
        "url": "https://github.com/Reactive-Extensions/RxJS",
        "favIconUrl": "https://assets-cdn.github.com/favicon.ico"
      },
      {
        "title": "RxJS/doc at master · Reactive-Extensions/RxJS",
        "url": "https://github.com/Reactive-Extensions/RxJS/tree/master/doc",
        "favIconUrl": "https://assets-cdn.github.com/favicon.ico"
      },
      {
        "title": "RxJS/examples at master · Reactive-Extensions/RxJS",
        "url": "https://github.com/Reactive-Extensions/RxJS/tree/master/examples",
        "favIconUrl": "https://assets-cdn.github.com/favicon.ico"
      },
      {
        "title": "RxJS/observable.md at master · Reactive-Extensions/RxJS",
        "url": "https://github.com/Reactive-Extensions/RxJS/blob/master/doc/api/core/observable.md",
        "favIconUrl": "https://assets-cdn.github.com/favicon.ico"
      },
      {
        "title": "Apache Spark™ - Lightning-Fast Cluster Computing",
        "url": "https://spark.apache.org/",
        "favIconUrl": "https://spark.apache.org/favicon.ico"
      },
      {
        "title": "Quick Start - Spark 1.3.1 Documentation",
        "url": "https://spark.apache.org/docs/latest/quick-start.html",
        "favIconUrl": "https://spark.apache.org/favicon.ico"
      },
      {
        "title": "Documentation | Apache Spark",
        "url": "http://spark.apache.org/documentation.html",
        "favIconUrl": "http://spark.apache.org/favicon.ico"
      },
      {
        "title": "Spark Programming Guide - Spark 1.3.1 Documentation",
        "url": "https://spark.apache.org/docs/latest/programming-guide.html",
        "favIconUrl": "https://spark.apache.org/favicon.ico"
      },
      {
        "title": "Spark SQL and DataFrames - Spark 1.3.1 Documentation",
        "url": "https://spark.apache.org/docs/latest/sql-programming-guide.html#rdds",
        "favIconUrl": "https://spark.apache.org/favicon.ico"
      },
      {
        "title": "Running Tachyon Locally - Tachyon 0.6.4 Documentation",
        "url": "http://tachyon-project.org/Running-Tachyon-Locally.html",
        "favIconUrl": "http://tachyon-project.org/favicon.ico"
      }
  ]
}